turf_mcp/__init__.py
turf_mcp/cli.py
turf_mcp/main.py
turf_mcp/utils.py
turf_mcp/server/__init__.py
turf_mcp/server/aggregation.py
turf_mcp/server/booleans.py
turf_mcp/server/classification.py
turf_mcp/server/coordinate_mutation.py
turf_mcp/server/data.py
turf_mcp/server/feature_conversion.py
turf_mcp/server/grid.py
turf_mcp/server/helper.py
turf_mcp/server/interpolation.py
turf_mcp/server/joins.py
turf_mcp/server/measurement.py
turf_mcp/server/misc.py
turf_mcp/server/random.py
turf_mcp/server/transformation.py
turf_mcp/server/unit_conversion.py
turf_mcp-0.2.2.dist-info/licenses/LICENSE
turf_mcp-0.2.2.dist-info/METADATA
turf_mcp-0.2.2.dist-info/WHEEL
turf_mcp-0.2.2.dist-info/entry_points.txt
turf_mcp-0.2.2.dist-info/top_level.txt
turf_mcp-0.2.2.dist-info/RECORD
