Metadata-Version: 2.4
Name: turf-mcp
Version: 0.2.2
Summary: 基于 Turf.js 构建的地理空间分析 MCP 服务。提供空间几何图形的测量、空间关系判断、坐标转换与偏移等核心功能。
Author-email: zhangjy07 <893928676@qq.com>
License: MIT
Project-URL: Homepage, https://github.com/zhangjy07/turf-mcp
Project-URL: Repository, https://github.com/zhangjy07/turf-mcp
Project-URL: Documentation, https://github.com/zhangjy07/turf-mcp#readme
Keywords: geospatial,analysis,turf,mcp,geometry
Classifier: Development Status :: 3 - Alpha
Classifier: Intended Audience :: Developers
Classifier: License :: OSI Approved :: MIT License
Classifier: Programming Language :: Python :: 3
Classifier: Programming Language :: Python :: 3.11
Classifier: Programming Language :: Python :: 3.12
Classifier: Programming Language :: Python :: 3.13
Classifier: Topic :: Scientific/Engineering :: GIS
Classifier: Topic :: Software Development :: Libraries :: Python Modules
Requires-Python: >=3.10
License-File: LICENSE
Requires-Dist: fastmcp>=2.12.5
Requires-Dist: pydantic>=2.12.3
Requires-Dist: httpx>=0.28.1
Dynamic: license-file
